kin/__init__.py
kin/kin.py
kin/kin_error_listener.py
kin/verifier.py
kin/grammar/PBXProj.g4
kin/grammar/PBXProj.interp
kin/grammar/PBXProj.tokens
kin/grammar/PBXProjLexer.interp
kin/grammar/PBXProjLexer.py
kin/grammar/PBXProjLexer.tokens
kin/grammar/PBXProjListener.py
kin/grammar/PBXProjParser.py
kin/grammar/__init__.py
kin-2.1.14.dist-info/entry_points.txt
kin-2.1.14.dist-info/licenses/LICENSE.txt
kin-2.1.14.dist-info/WHEEL
kin-2.1.14.dist-info/METADATA
kin-2.1.14.dist-info/RECORD
