Metadata-Version: 2.4
Name: kin
Version: 2.1.14
Summary: A simple project.pbxproj verifier
Keywords: xcode,project.pbxproj,lint,objective-c,swift,ios
Author-email: Serchinastico <oss@serchinastico.com>
Requires-Python: >=3.8
Classifier: Development Status :: 4 - Beta
Classifier: Intended Audience :: Developers
Classifier: License :: OSI Approved :: Apache Software License
Classifier: Programming Language :: Python :: 3
Classifier: Topic :: Software Development :: Build Tools
License-File: LICENSE.txt
Requires-Dist: antlr4-python3-runtime==4.13.1
Project-URL: Homepage, https://github.com/Serchinastico/Kin
